pyetf/__init__.py
pyetf/_clients.py
pyetf/etfdb.py
pyetf/utils.py
pyetfdb-1.0.0.dist-info/LICENSE
pyetfdb-1.0.0.dist-info/METADATA
pyetfdb-1.0.0.dist-info/WHEEL
pyetfdb-1.0.0.dist-info/top_level.txt
pyetfdb-1.0.0.dist-info/RECORD
