Metadata-Version: 2.1
Name: pyetfdb
Version: 1.0.0
Summary: ETF screening tool
Home-page: https://github.com/JakubPluta/pyetf/
Author: Jakub Pluta
Author-email: plutakuba@gmail.com
License: UNKNOWN
Platform: UNKNOWN
Classifier: Programming Language :: Python :: 3
Classifier: License :: OSI Approved :: MIT License
Classifier: Operating System :: OS Independent
Requires-Python: >=3.7
License-File: LICENSE
Requires-Dist: requests
Requires-Dist: pytest
Requires-Dist: bs4
Requires-Dist: pandas
Requires-Dist: aiohttp
Requires-Dist: async-retrying
Requires-Dist: aiohttp-retry
